{
    "07:00 - 08:30": [
        "07:00 - 08:30"
    ],
    "07:00 - 08:41": [
        "07:00 - 08:41"
    ],
    "07:00 - 10:15": [
        "07:00 - 08:30",
        "08:45 - 10:15"
    ],
    "07:00 - 10:30": [
        "07:00 - 08:30",
        "08:45 - 10:15"
    ],
    "07:00 - 10:36": [
        "07:00 - 08:41",
        "08:55 - 10:36"
    ],
    "07:00 - 10:37": [
        "07:00 - 08:30",
        "08:45 - 10:15",
        "10:30 - 12:00"
    ],
    "07:00 - 14:26": [
        "07:00 - 08:41",
        "08:55 - 10:36",
        "10:50 - 12:31",
        "12:45 - 14:26"
    ],
    "08:30 - 12:06": [
        "09:00 - 10:41",
        "10:55 - 12:36"
    ],
    "08:45 - 10:15": [
        "08:45 - 10:15"
    ],
    "08:45 - 10:26": [
        "08:55 - 10:36"
    ],
    "08:45 - 12:00": [
        "08:45 - 10:15",
        "10:30 - 12:00"
    ],
    "08:55 - 10:36": [
        "08:55 - 10:36"
    ],
    "08:55 - 12:31": [
        "08:55 - 10:36",
        "10:50 - 12:31"
    ],
    "08:55 - 16:21": [
        "08:55 - 10:36",
        "10:50 - 12:31",
        "12:45 - 14:26",
        "14:40 - 16:21"
    ],
    "09:00 - 12:36": [
        "09:00 - 10:41",
        "10:55 - 12:36"
    ],
    "09:30 - 20:15": [
        "08:55 - 10:36",
        "10:50 - 12:31",
        "12:45 - 14:26",
        "14:40 - 16:21"
    ],
    "10:30 - 12:00": [
        "10:30 - 12:00"
    ],
    "10:30 - 13:45": [
        "10:30 - 12:00",
        "12:30 - 14:00"
    ],
    "10:30 - 14:07": [
        "10:30 - 12:00",
        "12:30 - 14:00"
    ],
    "10:40 - 12:21": [
        "10:50 - 12:31"
    ],
    "10:40 - 14:10": [
        "10:30 - 12:00",
        "12:30 - 14:00"
    ],
    "10:50 - 12:31": [
        "10:50 - 12:31"
    ],
    "10:50 - 14:26": [
        "10:50 - 12:31",
        "12:45 - 14:26"
    ],
    "10:50 - 18:16": [
        "10:50 - 12:31",
        "12:45 - 14:26",
        "14:40 - 16:21",
        "16:35 - 18:16"
    ],
    "12:10 - 15:40": [
        "10:30 - 12:00",
        "12:30 - 14:00",
        "14:15 - 15:45"
    ],
    "12:10 - 15:47": [
        "12:30 - 14:00",
        "14:15 - 15:45"
    ],
    "12:15 - 13:45": [
        "12:30 - 14:00"
    ],
    "12:30 - 14:00": [
        "12:30 - 14:00"
    ],
    "12:30 - 15:45": [
        "12:30 - 14:00",
        "14:15 - 15:45"
    ],
    "12:45 - 14:26": [
        "12:45 - 14:26"
    ],
    "12:45 - 16:21": [
        "12:45 - 14:26",
        "14:40 - 16:21"
    ],
    "12:45 - 20:11": [
        "12:45 - 14:26",
        "14:40 - 16:21",
        "16:35 - 18:16",
        "18:30 - 20:11"
    ],
    "14:15 - 15:45": [
        "14:15 - 15:45"
    ],
    "14:15 - 17:30": [
        "14:15 - 15:45",
        "16:00 - 17:30"
    ],
    "14:40 - 16:21": [
        "14:40 - 16:21"
    ],
    "14:40 - 18:16": [
        "14:40 - 16:21",
        "16:35 - 18:16"
    ],
    "14:40 - 22:06": [
        "14:40 - 16:21",
        "16:35 - 18:16",
        "18:30 - 20:11",
        "20:25 - 22:06"
    ],
    "15:45 - 19:15": [
        "14:15 - 15:45",
        "16:00 - 17:30",
        "17:45 - 19:15"
    ],
    "16:00 - 17:30": [
        "16:00 - 17:30"
    ],
    "16:00 - 19:15": [
        "16:00 - 17:30",
        "17:45 - 19:15"
    ],
    "16:35 - 18:16": [
        "16:35 - 18:16"
    ],
    "16:35 - 20:11": [
        "16:35 - 18:16",
        "18:30 - 20:11"
    ],
    "17:45 - 19:15": [
        "17:45 - 19:15"
    ],
    "17:45 - 21:00": [
        "17:45 - 19:15",
        "19:30 - 21:00"
    ],
    "19:00 - 22:00": [
        "17:45 - 19:15",
        "19:30 - 21:00",
        "21:15 - 22:45"
    ],
    "19:00 - 22:37": [
        "17:45 - 19:15",
        "19:30 - 21:00",
        "21:15 - 22:45"
    ],
    "19:15 - 22:45": [
        "19:30 - 21:00",
        "21:15 - 22:45"
    ],
    "19:16 - 22:46": [
        "19:30 - 21:00",
        "21:15 - 22:45"
    ],
    "19:30 - 21:00": [
        "19:30 - 21:00"
    ],
    "19:30 - 22:45": [
        "19:30 - 21:00",
        "21:15 - 22:45"
    ],
    "21:15 - 22:45": [
        "21:15 - 22:45"
    ]
}